e_sim_game_scraper-0.0.12.dist-info/licenses/LICENSE
e_sim_game_scrapper/EsimScraper.py
e_sim_game_scrapper/__init__.py
e_sim_game_scrapper/utils.py
e_sim_game_scraper-0.0.12.dist-info/METADATA
e_sim_game_scraper-0.0.12.dist-info/WHEEL
e_sim_game_scraper-0.0.12.dist-info/top_level.txt
e_sim_game_scraper-0.0.12.dist-info/RECORD
