Metadata-Version: 2.4
Name: e-sim-game-scraper
Version: 0.0.12
Home-page: https://github.com/akiva-skolnik/e-sim-game-scraper
Author: Akiva
Author-email: akiva0003@gmail.com
Classifier: Programming Language :: Python :: 3
Classifier: License :: Other/Proprietary License
Classifier: Operating System :: OS Independent
License-File: LICENSE
Requires-Dist: lxml
Requires-Dist: requests
Dynamic: author
Dynamic: author-email
Dynamic: classifier
Dynamic: description
Dynamic: description-content-type
Dynamic: home-page
Dynamic: license-file
Dynamic: requires-dist
